cutlass/__init__.py
cutlass/library_defaults.py
cutlass/shape.py
cutlass/swizzle.py
cutlass/backend/__init__.py
cutlass/backend/arguments.py
cutlass/backend/c_types.py
cutlass/backend/compiler.py
cutlass/backend/conv2d_operation.py
cutlass/backend/epilogue.py
cutlass/backend/frontend.py
cutlass/backend/gemm_operation.py
cutlass/backend/library.py
cutlass/backend/memory_manager.py
cutlass/backend/operation.py
cutlass/backend/reduction_operation.py
cutlass/backend/type_hint.py
cutlass/backend/evt/__init__.py
cutlass/backend/evt/epilogue.py
cutlass/backend/evt/backend/__init__.py
cutlass/backend/evt/backend/emitter_base.py
cutlass/backend/evt/backend/sm80_emitter.py
cutlass/backend/evt/backend/sm80_nodes.py
cutlass/backend/evt/backend/sm90_emitter.py
cutlass/backend/evt/backend/sm90_nodes.py
cutlass/backend/evt/frontend/__init__.py
cutlass/backend/evt/frontend/frontend_base.py
cutlass/backend/evt/frontend/python_ast.py
cutlass/backend/evt/ir/__init__.py
cutlass/backend/evt/ir/compute_nodes.py
cutlass/backend/evt/ir/dag_ir.py
cutlass/backend/evt/ir/layout_algorithm.py
cutlass/backend/evt/ir/layout_nodes.py
cutlass/backend/evt/ir/load_nodes.py
cutlass/backend/evt/ir/node.py
cutlass/backend/evt/ir/store_nodes.py
cutlass/backend/evt/ir/tensor.py
cutlass/backend/evt/passes/__init__.py
cutlass/backend/evt/passes/graph_drawer.py
cutlass/backend/evt/passes/pass_argument_type.py
cutlass/backend/evt/passes/pass_dag_2_tree.py
cutlass/backend/evt/passes/pass_fix_element_d.py
cutlass/backend/evt/passes/pass_get_impl.py
cutlass/backend/evt/passes/pass_layout_elimination.py
cutlass/backend/evt/passes/pass_manager.py
cutlass/backend/evt/passes/pass_no_op_elimination.py
cutlass/backend/evt/passes/pass_preprocess_red.py
cutlass/backend/evt/passes/pass_shape_type_propagation.py
cutlass/backend/evt/passes/smem_size_calculator.py
cutlass/backend/evt/passes/util.py
cutlass/backend/utils/__init__.py
cutlass/backend/utils/device.py
cutlass/emit/__init__.py
cutlass/emit/common.py
nvidia_cutlass-3.8.0.0.dist-info/LICENSE.txt
nvidia_cutlass-3.8.0.0.dist-info/METADATA
nvidia_cutlass-3.8.0.0.dist-info/WHEEL
nvidia_cutlass-3.8.0.0.dist-info/top_level.txt
nvidia_cutlass-3.8.0.0.dist-info/RECORD
