Metadata-Version: 2.2
Name: nvidia-cutlass
Version: 3.8.0.0
Summary: CUTLASS
License: BSD-3-Clause
Project-URL: Homepage, https://github.com/nvidia/cutlass
Project-URL: Bug Tracker, https://github.com/nvidia/cutlass/issues
Classifier: Programming Language :: Python :: 3
Classifier: License :: OSI Approved :: BSD License
Classifier: Operating System :: OS Independent
Requires-Python: >=3.8
License-File: LICENSE.txt
Requires-Dist: cuda-python>=11.8.0
Requires-Dist: networkx
Requires-Dist: numpy
Requires-Dist: pydot
Requires-Dist: scipy
Requires-Dist: treelib
